[
    {
        "name": "박은선",
        "position": "기획자",
        "email": "p_dmstjs227@naver.com",
        "photo": "ensun.png",
        "link": "https://linkedin.com/in/eunseon-park-profile"
    },
    {
        "name": "박청명",
        "position": "기획자",
        "email": "crusoe1004@gmail.com",
        "photo": "chungmyung.png",
        "link": "https://open.kakao.com/o/sepDLfhc"
    },
    {
        "name": "박정은",
        "position": "디자이너",
        "email": "euny2772@gmail.com",
        "photo": "jungen.png",
        "link": "https://www.behance.net/euny2772a3f9"
    },
    {
        "name": "여지아",
        "position": "디자이너",
        "email": "jjiyomi@naver.com",
        "photo": "jia.png",
        "link": "https://www.instagram.com/dotoryfilm/"
    },
    {
        "name": "문용필",
        "position": "개발자",
        "email": "m71661@gmail.com",
        "photo": "yongpil.png",
        "link": "https://github.com/YongPilMoon"
    },
    {
        "name": "안재민",
        "position": "개발자",
        "email": "jae7415@gmail.com",
        "photo": "jemin.png",
        "link": "https://github.com/ippowe"
    },
    {
        "name": "이유성",
        "position": "개발자",
        "email": "lus0333@gmail.com",
        "photo": "yousung.png",
        "link": "https://github.com/yusunglee2074"
    },
    {
        "name": "이한국",
        "position": "PM/개발자",
        "email": "leekorea09@gmail.com",
        "photo": "hanguk.png",
        "link": "https://github.com/hans-hk"
    }
]